tests/__init__.py
tests/cli_test.py
tests/config_test.py
tests/core_test.py
tests/db_test.py
tests/notification_test.py
tests/scan_random_sites.py
tests/scan_test.py
tests/utils_test.py
tests/wpscan_test.py
wpwatcher/__init__.py
wpwatcher/__main__.py
wpwatcher/__version__.py
wpwatcher/cli.py
wpwatcher/config.py
wpwatcher/core.py
wpwatcher/daemon.py
wpwatcher/db.py
wpwatcher/email.py
wpwatcher/report.py
wpwatcher/scan.py
wpwatcher/site.py
wpwatcher/syslog.py
wpwatcher/utils.py
wpwatcher/wpscan.py
wpwatcher-3.0.7.dist-info/LICENSE
wpwatcher-3.0.7.dist-info/METADATA
wpwatcher-3.0.7.dist-info/WHEEL
wpwatcher-3.0.7.dist-info/entry_points.txt
wpwatcher-3.0.7.dist-info/top_level.txt
wpwatcher-3.0.7.dist-info/RECORD
