Metadata-Version: 2.1
Name: wpwatcher
Version: 3.0.7
Summary: WPWatcher - Automating WPScan to scan and report vulnerable Wordpress sites
Home-page: https://github.com/tristanlatr/WPWatcher
Maintainer: Florian Roth, Tristan Landes
License: Apache License 2.0
Keywords: wpscan auto multiple bulk batch scan wordpress email report alerts warnings service automate mass vulnerable sites asynchronous syslog
Classifier: Development Status :: 5 - Production/Stable
Classifier: Intended Audience :: Information Technology
Classifier: Environment :: Console
Classifier: Topic :: Security
Classifier: Topic :: Utilities
Classifier: Topic :: System :: Monitoring
Classifier: Programming Language :: Python :: 3
Classifier: Typing :: Typed
Classifier: License :: OSI Approved :: Apache Software License
Requires-Python: >=3.6
License-File: LICENSE
Requires-Dist: wpscan-out-parse (>=1.9.3)
Requires-Dist: filelock
Provides-Extra: dev
Requires-Dist: pytest ; extra == 'dev'
Requires-Dist: pytest-cov ; extra == 'dev'
Requires-Dist: codecov ; extra == 'dev'
Requires-Dist: coverage ; extra == 'dev'
Requires-Dist: tox ; extra == 'dev'
Requires-Dist: mypy ; extra == 'dev'
Provides-Extra: docs
Requires-Dist: Sphinx ; extra == 'docs'
Requires-Dist: recommonmark ; extra == 'docs'
Provides-Extra: syslog
Requires-Dist: rfc5424-logging-handler ; extra == 'syslog'
Requires-Dist: cefevent ; extra == 'syslog'
